ksyun/__init__.py
ksyun/client/__init__.py
ksyun/client/actiontrail/__init__.py
ksyun/client/actiontrail/v20190401/__init__.py
ksyun/client/actiontrail/v20190401/client.py
ksyun/client/actiontrail/v20190401/models.py
ksyun/client/bill/__init__.py
ksyun/client/bill/v20180601/__init__.py
ksyun/client/bill/v20180601/client.py
ksyun/client/bill/v20180601/models.py
ksyun/client/bill/v20220601/__init__.py
ksyun/client/bill/v20220601/client.py
ksyun/client/bill/v20220601/models.py
ksyun/client/bill_union/__init__.py
ksyun/client/bill_union/v20200101/__init__.py
ksyun/client/bill_union/v20200101/client.py
ksyun/client/bill_union/v20200101/models.py
ksyun/client/bill_union/v20221222/__init__.py
ksyun/client/bill_union/v20221222/client.py
ksyun/client/bill_union/v20221222/models.py
ksyun/client/bws/__init__.py
ksyun/client/bws/v20160304/__init__.py
ksyun/client/bws/v20160304/client.py
ksyun/client/bws/v20160304/models.py
ksyun/client/cdn/__init__.py
ksyun/client/cdn/v20160901/__init__.py
ksyun/client/cdn/v20160901/client.py
ksyun/client/cdn/v20160901/models.py
ksyun/client/cdn/v20200630/__init__.py
ksyun/client/cdn/v20200630/client.py
ksyun/client/cdn/v20200630/models.py
ksyun/client/cdn/v20200901/__init__.py
ksyun/client/cdn/v20200901/client.py
ksyun/client/cdn/v20200901/models.py
ksyun/client/cen/__init__.py
ksyun/client/cen/v20160304/__init__.py
ksyun/client/cen/v20160304/client.py
ksyun/client/cen/v20160304/models.py
ksyun/client/clickhouse/__init__.py
ksyun/client/clickhouse/v20210101/__init__.py
ksyun/client/clickhouse/v20210101/client.py
ksyun/client/clickhouse/v20210101/models.py
ksyun/client/client/__init__.py
ksyun/client/client/kcm/__init__.py
ksyun/client/client/kcm/v20160304/__init__.py
ksyun/client/client/kcm/v20160304/client.py
ksyun/client/client/kcm/v20160304/models.py
ksyun/client/ebs/__init__.py
ksyun/client/ebs/v20160304/__init__.py
ksyun/client/ebs/v20160304/client.py
ksyun/client/ebs/v20160304/models.py
ksyun/client/eip/__init__.py
kingsoftcloud_sdk_python_msh-1.5.3.dist-info/LICENSE
kingsoftcloud_sdk_python_msh-1.5.3.dist-info/METADATA
kingsoftcloud_sdk_python_msh-1.5.3.dist-info/WHEEL
kingsoftcloud_sdk_python_msh-1.5.3.dist-info/top_level.txt
kingsoftcloud_sdk_python_msh-1.5.3.dist-info/RECORD
